{
	"configurations" : 
	[
		{
			"directories" : 
			[
				{
					"build" : ".",
					"minimumCMakeVersion" : 
					{
						"string" : "2.8"
					},
					"projectIndex" : 0,
					"source" : ".",
					"targetIndexes" : 
					[
						0,
						1,
						2
					]
				}
			],
			"name" : "Debug",
			"projects" : 
			[
				{
					"directoryIndexes" : 
					[
						0
					],
					"name" : "string",
					"targetIndexes" : 
					[
						0,
						1,
						2
					]
				}
			],
			"targets" : 
			[
				{
					"directoryIndex" : 0,
					"id" : "string_contain::@6890427a1f51a3e7e1df",
					"jsonFile" : "target-string_contain-Debug-15d94ba969308326a068.json",
					"name" : "string_contain",
					"projectIndex" : 0
				},
				{
					"directoryIndex" : 0,
					"id" : "string_rotate::@6890427a1f51a3e7e1df",
					"jsonFile" : "target-string_rotate-Debug-7d126fe555b12763bf6b.json",
					"name" : "string_rotate",
					"projectIndex" : 0
				},
				{
					"directoryIndex" : 0,
					"id" : "word_rotate::@6890427a1f51a3e7e1df",
					"jsonFile" : "target-word_rotate-Debug-27a45b7f85fa66dc9ace.json",
					"name" : "word_rotate",
					"projectIndex" : 0
				}
			]
		}
	],
	"kind" : "codemodel",
	"paths" : 
	{
		"build" : "/home/ppf/leetcode_daily/build",
		"source" : "/home/ppf/leetcode_daily/DataStructure/string"
	},
	"version" : 
	{
		"major" : 2,
		"minor" : 0
	}
}
